{
  "main": {
    "id": "e8d15c7f5fd89717",
    "type": "split",
    "children": [
      {
        "id": "65d09e9e406209e0",
        "type": "tabs",
        "children": [
          {
            "id": "6092b91a43e93109",
            "type": "leaf",
            "state": {
              "type": "markdown",
              "state": {
                "file": "TO DO.md",
                "mode": "source",
                "source": false
              },
              "icon": "lucide-file",
              "title": "TO DO"
            }
          }
        ]
      }
    ],
    "direction": "vertical"
  },
  "left": {
    "id": "93aad7a7d012003a",
    "type": "split",
    "children": [
      {
        "id": "973b6084638862a9",
        "type": "tabs",
        "children": [
          {
            "id": "fab8ea269d4032b0",
            "type": "leaf",
            "state": {
              "type": "file-explorer",
              "state": {
                "sortOrder": "alphabetical",
                "autoReveal": false
              },
              "icon": "lucide-folder-closed",
              "title": "文件列表"
            }
          },
          {
            "id": "6aba829e7703cbc9",
            "type": "leaf",
            "state": {
              "type": "search",
              "state": {
                "query": "",
                "matchingCase": false,
                "explainSearch": false,
                "collapseAll": false,
                "extraContext": false,
                "sortOrder": "alphabetical"
              },
              "icon": "lucide-search",
              "title": "搜索"
            }
          },
          {
            "id": "f529671f2b6e419f",
            "type": "leaf",
            "state": {
              "type": "bookmarks",
              "state": {},
              "icon": "lucide-bookmark",
              "title": "书签"
            }
          }
        ]
      }
    ],
    "direction": "horizontal",
    "width": 238.50043487548828
  },
  "right": {
    "id": "e53ba686efe0ebef",
    "type": "split",
    "children": [
      {
        "id": "49b2bc219032c6e9",
        "type": "tabs",
        "children": [
          {
            "id": "3986980e26bd39fb",
            "type": "leaf",
            "state": {
              "type": "backlink",
              "state": {
                "file": "GKD_related/week5/Drawing 2025-04-10 22.04.34.excalidraw.md",
                "collapseAll": false,
                "extraContext": false,
                "sortOrder": "alphabetical",
                "showSearch": false,
                "searchQuery": "",
                "backlinkCollapsed": false,
                "unlinkedCollapsed": true
              },
              "icon": "links-coming-in",
              "title": "Drawing 2025-04-10 22.04.34.excalidraw 的反向链接列表"
            }
          },
          {
            "id": "00cd8f4579184e97",
            "type": "leaf",
            "state": {
              "type": "outgoing-link",
              "state": {
                "file": "操作系统/jyy操作系统/pstree/1.md",
                "linksCollapsed": false,
                "unlinkedCollapsed": true
              },
              "icon": "links-going-out",
              "title": "1 的出链列表"
            }
          },
          {
            "id": "cbc3f27e20168906",
            "type": "leaf",
            "state": {
              "type": "tag",
              "state": {
                "sortOrder": "frequency",
                "useHierarchy": true
              },
              "icon": "lucide-tags",
              "title": "标签"
            }
          },
          {
            "id": "6d5de72baf09ade3",
            "type": "leaf",
            "state": {
              "type": "outline",
              "state": {
                "file": "333.md",
                "followCursor": false,
                "showSearch": false,
                "searchQuery": ""
              },
              "icon": "lucide-list",
              "title": "333 的大纲"
            }
          },
          {
            "id": "1b3b96db1ff7def3",
            "type": "leaf",
            "state": {
              "type": "git-view",
              "state": {},
              "icon": "git-pull-request",
              "title": "Source Control"
            }
          }
        ],
        "currentTab": 3
      }
    ],
    "direction": "horizontal",
    "width": 300,
    "collapsed": true
  },
  "left-ribbon": {
    "hiddenItems": {
      "switcher:打开快速切换": false,
      "graph:查看关系图谱": false,
      "canvas:新建白板": false,
      "daily-notes:打开/创建今天的日记": false,
      "templates:插入模板": false,
      "command-palette:打开命令面板": false,
      "markdown-importer:打开 Markdown 格式转换器": false,
      "zk-prefixer:创建时间戳笔记": false,
      "random-note:开始漫游笔记": false,
      "workspaces:管理工作区布局": false,
      "obsidian-excalidraw-plugin:新建绘图文件": false,
      "obsidian-git:Open Git source control": false
    }
  },
  "active": "6092b91a43e93109",
  "lastOpenFiles": [
    "100日记/2025/2025-08-07.md",
    "100日记/2025/2025-07-11.md",
    "100日记/2025/2025-07-18.md",
    "000学习/电赛/运放/note.md",
    "未命名.canvas",
    "333.md",
    "000学习/电赛/运放",
    "300模板",
    "README.md",
    "100日记/2025/2025-04-21.md",
    "TO DO.md",
    "000学习/GKD_related/电控基础/串口和控制.md",
    "000学习/GKD_related/电控问题.md",
    "000学习/GKD_related/电控基础",
    "000学习/深度学习/ZOMI-自动微分/note.md",
    "000学习/深度学习/ZOMI-自动微分/Pasted image 20250719041455.png",
    "000学习/深度学习/ZOMI-自动微分/Pasted image 20250719041338.png",
    "000学习/深度学习/ZOMI-自动微分/Pasted image 20250719041212.png",
    "000学习/深度学习/ZOMI-自动微分/Pasted image 20250719040936.png",
    "000学习/深度学习/ZOMI-自动微分/Pasted image 20250719040718.png",
    "000学习/深度学习/ZOMI-自动微分/Pasted image 20250719040401.png",
    "000学习/深度学习/ZOMI-自动微分/Pasted image 20250719032848.png",
    "000学习/深度学习/ZOMI-自动微分/Pasted image 20250719032733.png",
    "000学习/深度学习/ZOMI-自动微分/Pasted image 20250719032552.png",
    "000学习/深度学习/ZOMI-自动微分/Pasted image 20250719032427.png",
    "000学习/深度学习/CMU10-414/note.md",
    "000学习/深度学习/ZOMI-自动微分",
    "000学习/Linux网络编程/Note.md",
    "000学习/Linux网络编程/socket函数详解.md",
    "000学习/深度学习/CS329P实用机器学习/从零开始的机器学习之旅.md",
    "000学习/C++/CS106L/Streams.md",
    "000学习/C++/CS106B/Assignment 1.md",
    "000学习/C++/CS106B/Assignment3.md",
    "000学习/C++/CS106B/Assignment2.md",
    "000学习/深度学习",
    "000学习/电赛/赛题/2024H题小车.md",
    "000学习/电赛/图像处理算法/快速线性回归巡线.md",
    "000学习/电赛/赛题",
    "000学习/电赛/2024H题小车",
    "000学习/电赛/图像处理算法/Apriltag视觉基准系统.md",
    "000学习/电赛/图像处理算法/Canny边缘检测.md",
    "000学习/电赛/k230/杂记.md",
    "100日记/2025/2025-05-01 02.md",
    "100日记/2025/2025-05-25.md",
    "000学习/电赛/图像处理算法",
    "000学习",
    "000学习/深度学习/CMU10-414",
    "000学习/C++/白板.canvas",
    "linux工具/nvim/未命名.canvas",
    "000学习/操作系统/jyy操作系统/pstree/pstree.canvas"
  ]
}